mtl_agent/__init__.py
mtl_agent/__main__.py
mtl_agent/thumbnail.py
mtl_agent/translate_subtitle.py
mtl_agent/upload_videos.py
mtl_agent/video_work.py
mtl_agent/providers/base.py
mtl_agent-0.3.3.dist-info/METADATA
mtl_agent-0.3.3.dist-info/WHEEL
mtl_agent-0.3.3.dist-info/entry_points.txt
mtl_agent-0.3.3.dist-info/RECORD
