Metadata-Version: 2.4
Name: mtl_agent
Version: 0.3.3
Summary: MTL agent for media processing
Author-email: Matey Krastev <matey.krastev@outlook.com>
License: MIT
Requires-Python: >=3.7
Requires-Dist: ass
Requires-Dist: ass-tag-parser
Requires-Dist: better-ffmpeg-progress
Requires-Dist: ffmpeg-python
Requires-Dist: pillow
Requires-Dist: playwright
Requires-Dist: requests
